quicklooks/__init__.py
quicklooks/bar_plot.py
quicklooks/chart_skeleton.py
quicklooks/cs_attributes.py
quicklooks/dist_plot.py
quicklooks/legend.py
quicklooks/line_plot.py
quicklooks/plot_and_text_styling.py
quicklooks/reference_line.py
quicklooks/save_chart.py
quicklooks/scatter_plot.py
quicklooks/templates.py
quicklooks/text.py
quicklooks/fonts/lato/text.ttf
quicklooks/fonts/lato/title.ttf
quicklooks/fonts/montserrat/text.ttf
quicklooks/fonts/montserrat/title.ttf
quicklooks/fonts/oswald/text.ttf
quicklooks/fonts/oswald/title.ttf
quicklooks/fonts/roboto/text.ttf
quicklooks/fonts/roboto/title.ttf
quicklooks/fonts/rubik/text.ttf
quicklooks/fonts/rubik/title.ttf
quicklooks/fonts/source_sans/text.ttf
quicklooks/fonts/source_sans/title.ttf
quicklooks/fonts/work_sans/text.ttf
quicklooks/fonts/work_sans/title.ttf
quicklooks-1.0.8.dist-info/licenses/LICENSE
quicklooks-1.0.8.dist-info/METADATA
quicklooks-1.0.8.dist-info/WHEEL
quicklooks-1.0.8.dist-info/top_level.txt
quicklooks-1.0.8.dist-info/RECORD
