Metadata-Version: 2.4
Name: quicklooks
Version: 1.0.8
Summary: quicklook is a Python package for visualizing data quickly using matplotlib.
Home-page: https://github.com/alexdsbreslav/quicklooks
Author: Alex Breslav
Author-email: alexdsbreslav@gmail.com
License: MIT
Keywords: matplotlib,data-visualization,python
Classifier: Development Status :: 3 - Alpha
Classifier: License :: OSI Approved :: MIT License
Classifier: Programming Language :: Python :: 3.9
Classifier: Programming Language :: Python :: 3.10
Classifier: Programming Language :: Python :: 3.11
Classifier: Programming Language :: Python :: 3.12
License-File: LICENSE
Requires-Dist: numpy
Requires-Dist: matplotlib
Requires-Dist: pandas
Requires-Dist: datetime
Requires-Dist: seaborn
Dynamic: author
Dynamic: author-email
Dynamic: classifier
Dynamic: description
Dynamic: description-content-type
Dynamic: home-page
Dynamic: keywords
Dynamic: license
Dynamic: license-file
Dynamic: requires-dist
Dynamic: summary
